{ 
    
    "Armadilha3": [
        {
            "shape": [ 13,31, 0,38, 7,18 ]
        },
        {
            "shape": [ 60,38, 46,31, 50,18 ]
        },
        {
            "shape": [ 25,31, 13,31, 19,11 ]
        },
        {
            "shape": [ 46,31, 60,38, 0,38, 13,31 ]
        },
        {
            "shape": [ 25,31, 33,0, 37,0, 46,31 ]
        }
    ]
    , 
    "poderAumenta": [
        {
            "shape": [ 26,9, 59,4, 80,14, 96,40, 96,60, 19,86, 8,73, 3,40 ]
        },
        {
            "shape": [ 40,96, 19,86, 96,60, 73,91 ]
        }
    ]
    , 
    "Poderes": [
        {
            "shape": [ 400,109, 416,246, 371,339, 234,407, 103,378, 7,262, 123,0, 294,0 ]
        },
        {
            "shape": [ 123,0, 7,262, 15,105 ]
        }
    ]
    , 
    "QueijoBom": [
        {
            "shape": [ 0,930, 450,30, 600,0, 1020,150, 1320,360, 1320,1020, 0,1500 ]
        }
    ]
    , 
    "QueijoVenenoso": [
        {
            "shape": [ 0,930, 450,30, 600,0, 1020,150, 1320,360, 1320,1020, 0,1500 ]
        }
    ]
    , 
    "Toca": [
        {
            "shape": [ 325,51, 299,12, 325,26 ]
        },
        {
            "shape": [ 351,90, 326,286, 325,51, 351,65 ]
        },
        {
            "shape": [ 326,286, 351,90, 364,116, 365,260, 351,286 ]
        },
        {
            "shape": [ 364,116, 351,90, 364,91 ]
        },
        {
            "shape": [ 38,78, 25,104, 26,78 ]
        },
        {
            "shape": [ 0,156, 12,156, 326,286, 325,299, 0,299 ]
        },
        {
            "shape": [ 25,104, 12,156, 13,104 ]
        },
        {
            "shape": [ 116,13, 12,156, 25,104, 38,78, 91,13 ]
        },
        {
            "shape": [ 377,260, 365,260, 364,116, 377,117 ]
        },
        {
            "shape": [ 326,286, 12,156, 299,12, 325,51 ]
        },
        {
            "shape": [ 299,0, 116,13, 117,0 ]
        },
        {
            "shape": [ 299,0, 299,12, 12,156, 116,13 ]
        }
    ]
    , 
    "TocaInvertida": [
        {
            "shape": [ 26,274, 52,287, 26,286 ]
        },
        {
            "shape": [ 64,26, 51,52, 52,26 ]
        },
        {
            "shape": [ 286,25, 260,12, 286,13 ]
        },
        {
            "shape": [ 52,299, 52,287, 364,155, 377,156, 377,299 ]
        },
        {
            "shape": [ 51,52, 260,0, 260,12, 52,287, 12,117, 26,65 ]
        },
        {
            "shape": [ 364,155, 351,103, 364,104 ]
        },
        {
            "shape": [ 351,103, 286,25, 351,78 ]
        },
        {
            "shape": [ 0,117, 12,117, 52,287, 0,260 ]
        },
        {
            "shape": [ 364,155, 52,287, 260,12, 286,25, 351,103 ]
        },
        {
            "shape": [ 260,0, 51,52, 78,0 ]
        }
    ]
}
